[
    {
        "date": "2017-03-16",
        "A_Cinderella_Story": 0.5118827562,
        "Beauties_and_the_Beast": 0.3767200358,
        "Black_Mamba": 0.4921252481,
        "Class Median": 0.3026375375,
        "Component": 0.4598663634,
        "FOURdham_Marchketeers": 0.4535677753,
        "Gambler": 0.4095218463,
        "InMotion": 0.3048504518,
        "Never_Blow_3-1": 0.3533992868,
        "OneBillionDollars": 0.4704720604,
        "SuperDC": 0.351513897,
        "Team_RNG": 0.6787492688,
        "Team_Rams": 0.33621328,
        "Team_Slam_Dunk": 0.3249279868,
        "mercury": 0.4951628372,
        "pilarz": 0.424638061,
        "team_18": 0.4594867043,
        "team_Four-point shot": 0.4604039501
    },
    {
        "date": "2017-03-17",
        "A_Cinderella_Story": 0.6145803662,
        "Beauties_and_the_Beast": 0.3552555888,
        "Black_Mamba": 0.5124208415,
        "Class Median": 0.5349000107,
        "Component": 0.4482193466,
        "FOURdham_Marchketeers": 0.4222422888,
        "Gambler": 0.5337209907,
        "InMotion": 0.3274695843,
        "Never_Blow_3-1": 0.3467810302,
        "OneBillionDollars": 0.4674006672,
        "SuperDC": 0.3317761614,
        "Team_RNG": 0.7247904582,
        "Team_Rams": 0.3623848242,
        "Team_Slam_Dunk": 0.3216205245,
        "mercury": 0.4700712437,
        "pilarz": 0.3916361172,
        "team_18": 0.4459686382,
        "team_Four-point shot": 0.5026975742
    },
    {
        "date": "2017-03-18",
        "A_Cinderella_Story": 0.7660528345,
        "Beauties_and_the_Beast": 0.4731534983,
        "Black_Mamba": 0.5715134481,
        "Class Median": 0.5084729903,
        "Component": 0.5191849366,
        "FOURdham_Marchketeers": 0.5242912688,
        "Gambler": 0.5731436993,
        "InMotion": 0.4100777458,
        "Never_Blow_3-1": 0.422000073,
        "OneBillionDollars": 0.5315911401,
        "SuperDC": 0.4337739333,
        "Team_RNG": 0.7103561891,
        "Team_Rams": 0.4403450356,
        "Team_Slam_Dunk": 0.4054918927,
        "mercury": 0.5159963695,
        "pilarz": 0.482142011,
        "team_18": 0.5146819017,
        "team_Four-point shot": 0.6140258093
    },
    {
        "date": "2017-03-19",
        "A_Cinderella_Story": 0.7251663576,
        "Beauties_and_the_Beast": 0.4686227511,
        "Black_Mamba": 0.5724728614,
        "Class Median": 0.5449851173,
        "Component": 0.5517872208,
        "FOURdham_Marchketeers": 0.5156870726,
        "Gambler": 0.5724280176,
        "InMotion": 0.4228787131,
        "Never_Blow_3-1": 0.4642845687,
        "OneBillionDollars": 0.5433790613,
        "SuperDC": 0.439765688,
        "Team_RNG": 0.7270546482,
        "Team_Rams": 0.45237256,
        "Team_Slam_Dunk": 0.4215062722,
        "mercury": 0.5392394659,
        "pilarz": 0.4947588224,
        "team_18": 0.5210203738,
        "team_Four-point shot": 0.6024850473
    },
    {
        "date": "2017-03-23",
        "A_Cinderella_Story": 0.7963558061,
        "Beauties_and_the_Beast": 0.5046983864,
        "Black_Mamba": 0.6056113796,
        "Class Median": 0.5347570834,
        "Component": 0.5653601406,
        "FOURdham_Marchketeers": 0.5688697279,
        "Gambler": 0.617772587,
        "InMotion": 0.454464767,
        "Never_Blow_3-1": 0.4934927261,
        "OneBillionDollars": 0.5640632003,
        "SuperDC": 0.4762379916,
        "Team_RNG": 0.7407651135,
        "Team_Rams": 0.4831571877,
        "Team_Slam_Dunk": 0.4563705305,
        "mercury": 0.5551823501,
        "pilarz": 0.5227265665,
        "team_18": 0.5425118091,
        "team_Four-point shot": 0.6228177763
    },
    {
        "date": "2017-03-24",
        "A_Cinderella_Story": 0.7469962574,
        "Beauties_and_the_Beast": 0.4929403692,
        "Black_Mamba": 0.59820895,
        "Class Median": 0.5524620926,
        "Component": 0.5578631922,
        "FOURdham_Marchketeers": 0.5471061911,
        "Gambler": 0.6326577021,
        "InMotion": 0.4570746251,
        "Never_Blow_3-1": 0.4901465784,
        "OneBillionDollars": 0.5610866314,
        "SuperDC": 0.4753931716,
        "Team_RNG": 0.7395702661,
        "Team_Rams": 0.4842760342,
        "Team_Slam_Dunk": 0.4581548041,
        "mercury": 0.5616972405,
        "pilarz": 0.5181164438,
        "team_18": 0.5354722218,
        "team_Four-point shot": 0.5951615102
    },
    {
        "date": "2017-03-25",
        "A_Cinderella_Story": 0.7780278602,
        "Beauties_and_the_Beast": 0.4999226781,
        "Black_Mamba": 0.5956340123,
        "Class Median": 0.5417009959,
        "Component": 0.554879644,
        "FOURdham_Marchketeers": 0.5467922163,
        "Gambler": 0.6219139292,
        "InMotion": 0.4660268224,
        "Never_Blow_3-1": 0.4966264535,
        "OneBillionDollars": 0.5689423602,
        "SuperDC": 0.4902250284,
        "Team_RNG": 0.7370358974,
        "Team_Rams": 0.4920079247,
        "Team_Slam_Dunk": 0.4658646831,
        "mercury": 0.5585563995,
        "pilarz": 0.5251581872,
        "team_18": 0.542442804,
        "team_Four-point shot": 0.6253744603
    },
    {
        "date": "2017-03-26",
        "A_Cinderella_Story": 0.8127231054,
        "Beauties_and_the_Beast": 0.5102046601,
        "Black_Mamba": 0.6041659992,
        "Class Median": 0.5450962256,
        "Component": 0.5529758141,
        "FOURdham_Marchketeers": 0.5456378336,
        "Gambler": 0.6229327647,
        "InMotion": 0.4747591467,
        "Never_Blow_3-1": 0.5055625701,
        "OneBillionDollars": 0.5777399507,
        "SuperDC": 0.4988110166,
        "Team_RNG": 0.7400472736,
        "Team_Rams": 0.5003919889,
        "Team_Slam_Dunk": 0.4759439923,
        "mercury": 0.565623333,
        "pilarz": 0.5350522754,
        "team_18": 0.547842586,
        "team_Four-point shot": 0.6456257649
    },
    {
        "date": "2017-04-01",
        "A_Cinderella_Story": 0.7877115264,
        "Beauties_and_the_Beast": 0.5066403098,
        "Black_Mamba": 0.5968391256,
        "Class Median": 0.5777171907,
        "Component": 0.5443855796,
        "FOURdham_Marchketeers": 0.5521692074,
        "Gambler": 0.6745656349,
        "InMotion": 0.4702397321,
        "Never_Blow_3-1": 0.4984833905,
        "OneBillionDollars": 0.5710753879,
        "SuperDC": 0.4905580469,
        "Team_RNG": 0.7407667425,
        "Team_Rams": 0.4904321247,
        "Team_Slam_Dunk": 0.4696771412,
        "mercury": 0.556329091,
        "pilarz": 0.5254669852,
        "team_18": 0.5498254557,
        "team_Four-point shot": 0.636041393
    }
]