[{"id":"R1W1","scores":[{"team":"Beauties_and_the_Beast","prob_final":0.9798},{"team":"Black_Mamba","prob_final":0.99999},{"team":"Component","prob_final":0.990139},{"team":"FOURdham_Marchketeers","prob_final":0.974},{"team":"Gambler","prob_final":0.79},{"team":"InMotion","prob_final":0.998599},{"team":"mercury","prob_final":0.918886},{"team":"Never_Blow_3-1","prob_final":0.943086},{"team":"OneBillionDollars","prob_final":0.7438},{"team":"pilarz","prob_final":0.969567},{"team":"SuperDC","prob_final":0.996},{"team":"team_18","prob_final":0.925327},{"team":"team_Four-point shot","prob_final":0.586343},{"team":"Team_Rams","prob_final":0.987698},{"team":"Team_RNG","prob_final":0.558},{"team":"Team_Slam_Dunk","prob_final":0.991816},{"team":"A_Cinderella_Story","prob_final":0.038295}]},{"id":"R1W2","scores":[{"team":"Beauties_and_the_Beast","prob_final":0.9798},{"team":"Black_Mamba","prob_final":0.99999},{"team":"Component","prob_final":0.990139},{"team":"FOURdham_Marchketeers","prob_final":0.974},{"team":"Gambler","prob_final":0.79},{"team":"InMotion","prob_final":0.998599},{"team":"mercury","prob_final":0.918886},{"team":"Never_Blow_3-1","prob_final":0.943086},{"team":"OneBillionDollars","prob_final":0.7438},{"team":"pilarz","prob_final":0.969567},{"team":"SuperDC","prob_final":0.996},{"team":"team_18","prob_final":0.925327},{"team":"team_Four-point shot","prob_final":0.586343},{"team":"Team_Rams","prob_final":0.987698},{"team":"Team_RNG","prob_final":0.558},{"team":"Team_Slam_Dunk","prob_final":0.991816},{"team":"A_Cinderella_Story","prob_final":0.038295}]}]